{
  "regex-automata/src/util/determinize/state.rs:764:11:764:27": [
    {
      "Bool": {
        "Binary": {
          "kind": "Ge",
          "expr": "n >= 0b1000_0000",
          "lhs": "n",
          "rhs": "0b1000_0000",
          "cmp_with_int": true
        }
      }
    }
  ],
  "regex-automata/src/util/determinize/state.rs:765:19:765:43": [
    {
      "Bool": {
        "Binary": {
          "kind": "Other",
          "expr": "n.low_u8() | 0b1000_0000",
          "lhs": "n.low_u8()",
          "rhs": "0b1000_0000",
          "cmp_with_int": true
        }
      }
    }
  ]
}