{
  "regex-lite/src/string.rs:2616:11:2616:22": [
    {
      "Match": {
        "match_source": "regex-lite/src/string.rs:2616:11:2616:22",
        "match_str": "s.find('$')",
        "match_kind": {
          "Enum": [
            "None",
            "Some"
          ]
        },
        "arms": {
          "regex-lite/src/string.rs:2618:9:2618:13": {
            "pat": {
              "pat_str": "None",
              "kind": {
                "Enum": 0
              }
            },
            "guard": null,
            "body_source": "regex-lite/src/string.rs:2618:17:2618:39"
          },
          "regex-lite/src/string.rs:2617:9:2617:16": {
            "pat": {
              "pat_str": "Some(_)",
              "kind": {
                "Enum": 1
              }
            },
            "guard": null,
            "body_source": "regex-lite/src/string.rs:2617:20:2617:24"
          }
        }
      }
    }
  ]
}