{
  "regex-automata/src/dfa/onepass.rs:1978:13:1978:22": [
    {
      "Bool": {
        "Other": "utf8empty"
      }
    }
  ],
  "regex-automata/src/dfa/onepass.rs:1986:12:1986:45": [
    {
      "Bool": {
        "Binary": {
          "kind": "Eq",
          "expr": "self.get_nfa().pattern_len() == 1",
          "lhs": "self.get_nfa().pattern_len()",
          "rhs": "1",
          "cmp_with_int": true
        }
      }
    }
  ],
  "regex-automata/src/dfa/onepass.rs:1977:55:1977:79": [
    {
      "Bool": {
        "Other": "self.get_nfa().is_utf8()"
      }
    }
  ],
  "regex-automata/src/dfa/onepass.rs:1988:23:1988:76": [
    {
      "Try": "self.try_search_slots_imp(cache, input, &mut enough)?"
    }
  ],
  "regex-automata/src/dfa/onepass.rs:1977:25:1977:51": [
    {
      "Bool": {
        "Other": "self.get_nfa().has_empty()"
      }
    }
  ],
  "regex-automata/src/dfa/onepass.rs:1995:19:1995:72": [
    {
      "Try": "self.try_search_slots_imp(cache, input, &mut enough)?"
    }
  ],
  "regex-automata/src/dfa/onepass.rs:1983:12:1983:30": [
    {
      "Bool": {
        "Binary": {
          "kind": "Ge",
          "expr": "slots.len() >= min",
          "lhs": "slots.len()",
          "rhs": "min",
          "cmp_with_int": false
        }
      }
    }
  ]
}