{
  "name": "regex_automata::nfa::thompson::compiler::{impl#4}::c_look",
  "mod_info": {
    "name": "nfa::thompson::compiler",
    "loc": "regex-automata/src/nfa/thompson/mod.rs:60:1:60:14"
  },
  "visible": false,
  "loc": "regex-automata/src/nfa/thompson/compiler.rs:1550:5:1573:6",
  "doc": "/// Compile the given HIR look-around assertion to an NFA look-around\n/// assertion.\n",
  "code": [
    "fn c_look(&self, anchor: &hir::Look) -> Result<ThompsonRef, BuildError> {",
    "    let look = match *anchor {",
    "        hir::Look::Start => Look::Start,",
    "        hir::Look::End => Look::End,",
    "        hir::Look::StartLF => Look::StartLF,",
    "        hir::Look::EndLF => Look::EndLF,",
    "        hir::Look::StartCRLF => Look::StartCRLF,",
    "        hir::Look::EndCRLF => Look::EndCRLF,",
    "        hir::Look::WordAscii => Look::WordAscii,",
    "        hir::Look::WordAsciiNegate => Look::WordAsciiNegate,",
    "        hir::Look::WordUnicode => Look::WordUnicode,",
    "        hir::Look::WordUnicodeNegate => Look::WordUnicodeNegate,",
    "        hir::Look::WordStartAscii => Look::WordStartAscii,",
    "        hir::Look::WordEndAscii => Look::WordEndAscii,",
    "        hir::Look::WordStartUnicode => Look::WordStartUnicode,",
    "        hir::Look::WordEndUnicode => Look::WordEndUnicode,",
    "        hir::Look::WordStartHalfAscii => Look::WordStartHalfAscii,",
    "        hir::Look::WordEndHalfAscii => Look::WordEndHalfAscii,",
    "        hir::Look::WordStartHalfUnicode => Look::WordStartHalfUnicode,",
    "        hir::Look::WordEndHalfUnicode => Look::WordEndHalfUnicode,",
    "    };",
    "    let id = self.add_look(look)?;",
    "    Ok(ThompsonRef { start: id, end: id })",
    "}"
  ],
  "size": {
    "chain": 36,
    "contra": 0,
    "min_set": 18
  },
  "cond_chains": [
    {
      "id": 1,
      "conds": [
        {
          "cond": "*anchor matches hir::Look::WordEndHalfUnicode",
          "norm": null,
          "value": "true",
          "line": 1551,
          "bound": null
        },
        {
          "cond": "self.add_look(look)?",
          "norm": null,
          "value": "Err/None",
          "line": 1571,
          "bound": null
        }
      ],
      "ret": null,
      "path": [
        0,
        19,
        37,
        38,
        39,
        41,
        43,
        44,
        46,
        47,
        48
      ],
      "may_contra": false,
      "min_set": false
    },
    {
      "id": 2,
      "conds": [
        {
          "cond": "*anchor matches hir::Look::WordEndHalfUnicode",
          "norm": null,
          "value": "true",
          "line": 1551,
          "bound": null
        },
        {
          "cond": "self.add_look(look)?",
          "norm": null,
          "value": "Ok/Some",
          "line": 1571,
          "bound": null
        }
      ],
      "ret": "Ok(ThompsonRef { start: id, end: id })",
      "path": [
        0,
        19,
        37,
        38,
        39,
        42,
        45,
        48
      ],
      "may_contra": false,
      "min_set": true
    },
    {
      "id": 3,
      "conds": [
        {
          "cond": "*anchor matches hir::Look::WordStartHalfUnicode",
          "norm": null,
          "value": "true",
          "line": 1551,
          "bound": null
        },
        {
          "cond": "*anchor matches hir::Look::WordStartHalfUnicode",
          "norm": null,
          "value": "true",
          "line": 1551,
          "bound": null
        },
        {
          "cond": "self.add_look(look)?",
          "norm": null,
          "value": "Err/None",
          "line": 1571,
          "bound": null
        }
      ],
      "ret": null,
      "path": [
        0,
        18,
        36,
        37,
        38,
        39,
        41,
        43,
        44,
        46,
        47,
        48
      ],
      "may_contra": false,
      "min_set": false
    },
    {
      "id": 4,
      "conds": [
        {
          "cond": "*anchor matches hir::Look::WordStartHalfUnicode",
          "norm": null,
          "value": "true",
          "line": 1551,
          "bound": null
        },
        {
          "cond": "*anchor matches hir::Look::WordStartHalfUnicode",
          "norm": null,
          "value": "true",
          "line": 1551,
          "bound": null
        },
        {
          "cond": "self.add_look(look)?",
          "norm": null,
          "value": "Ok/Some",
          "line": 1571,
          "bound": null
        }
      ],
      "ret": "Ok(ThompsonRef { start: id, end: id })",
      "path": [
        0,
        18,
        36,
        37,
        38,
        39,
        42,
        45,
        48
      ],
      "may_contra": false,
      "min_set": true
    },
    {
      "id": 5,
      "conds": [
        {
          "cond": "*anchor matches hir::Look::WordEndHalfAscii",
          "norm": null,
          "value": "true",
          "line": 1551,
          "bound": null
        },
        {
          "cond": "*anchor matches hir::Look::WordEndHalfAscii",
          "norm": null,
          "value": "true",
          "line": 1551,
          "bound": null
        },
        {
          "cond": "self.add_look(look)?",
          "norm": null,
          "value": "Err/None",
          "line": 1571,
          "bound": null
        }
      ],
      "ret": null,
      "path": [
        0,
        17,
        35,
        37,
        38,
        39,
        41,
        43,
        44,
        46,
        47,
        48
      ],
      "may_contra": false,
      "min_set": false
    },
    {
      "id": 6,
      "conds": [
        {
          "cond": "*anchor matches hir::Look::WordEndHalfAscii",
          "norm": null,
          "value": "true",
          "line": 1551,
          "bound": null
        },
        {
          "cond": "*anchor matches hir::Look::WordEndHalfAscii",
          "norm": null,
          "value": "true",
          "line": 1551,
          "bound": null
        },
        {
          "cond": "self.add_look(look)?",
          "norm": null,
          "value": "Ok/Some",
          "line": 1571,
          "bound": null
        }
      ],
      "ret": "Ok(ThompsonRef { start: id, end: id })",
      "path": [
        0,
        17,
        35,
        37,
        38,
        39,
        42,
        45,
        48
      ],
      "may_contra": false,
      "min_set": true
    },
    {
      "id": 7,
      "conds": [
        {
          "cond": "*anchor matches hir::Look::WordStartHalfAscii",
          "norm": null,
          "value": "true",
          "line": 1551,
          "bound": null
        },
        {
          "cond": "*anchor matches hir::Look::WordStartHalfAscii",
          "norm": null,
          "value": "true",
          "line": 1551,
          "bound": null
        },
        {
          "cond": "self.add_look(look)?",
          "norm": null,
          "value": "Err/None",
          "line": 1571,
          "bound": null
        }
      ],
      "ret": null,
      "path": [
        0,
        16,
        34,
        37,
        38,
        39,
        41,
        43,
        44,
        46,
        47,
        48
      ],
      "may_contra": false,
      "min_set": false
    },
    {
      "id": 8,
      "conds": [
        {
          "cond": "*anchor matches hir::Look::WordStartHalfAscii",
          "norm": null,
          "value": "true",
          "line": 1551,
          "bound": null
        },
        {
          "cond": "*anchor matches hir::Look::WordStartHalfAscii",
          "norm": null,
          "value": "true",
          "line": 1551,
          "bound": null
        },
        {
          "cond": "self.add_look(look)?",
          "norm": null,
          "value": "Ok/Some",
          "line": 1571,
          "bound": null
        }
      ],
      "ret": "Ok(ThompsonRef { start: id, end: id })",
      "path": [
        0,
        16,
        34,
        37,
        38,
        39,
        42,
        45,
        48
      ],
      "may_contra": false,
      "min_set": true
    },
    {
      "id": 9,
      "conds": [
        {
          "cond": "*anchor matches hir::Look::WordEndUnicode",
          "norm": null,
          "value": "true",
          "line": 1551,
          "bound": null
        },
        {
          "cond": "*anchor matches hir::Look::WordEndUnicode",
          "norm": null,
          "value": "true",
          "line": 1551,
          "bound": null
        },
        {
          "cond": "self.add_look(look)?",
          "norm": null,
          "value": "Err/None",
          "line": 1571,
          "bound": null
        }
      ],
      "ret": null,
      "path": [
        0,
        15,
        33,
        37,
        38,
        39,
        41,
        43,
        44,
        46,
        47,
        48
      ],
      "may_contra": false,
      "min_set": false
    },
    {
      "id": 10,
      "conds": [
        {
          "cond": "*anchor matches hir::Look::WordEndUnicode",
          "norm": null,
          "value": "true",
          "line": 1551,
          "bound": null
        },
        {
          "cond": "*anchor matches hir::Look::WordEndUnicode",
          "norm": null,
          "value": "true",
          "line": 1551,
          "bound": null
        },
        {
          "cond": "self.add_look(look)?",
          "norm": null,
          "value": "Ok/Some",
          "line": 1571,
          "bound": null
        }
      ],
      "ret": "Ok(ThompsonRef { start: id, end: id })",
      "path": [
        0,
        15,
        33,
        37,
        38,
        39,
        42,
        45,
        48
      ],
      "may_contra": false,
      "min_set": true
    },
    {
      "id": 11,
      "conds": [
        {
          "cond": "*anchor matches hir::Look::WordStartUnicode",
          "norm": null,
          "value": "true",
          "line": 1551,
          "bound": null
        },
        {
          "cond": "*anchor matches hir::Look::WordStartUnicode",
          "norm": null,
          "value": "true",
          "line": 1551,
          "bound": null
        },
        {
          "cond": "self.add_look(look)?",
          "norm": null,
          "value": "Err/None",
          "line": 1571,
          "bound": null
        }
      ],
      "ret": null,
      "path": [
        0,
        14,
        32,
        37,
        38,
        39,
        41,
        43,
        44,
        46,
        47,
        48
      ],
      "may_contra": false,
      "min_set": false
    },
    {
      "id": 12,
      "conds": [
        {
          "cond": "*anchor matches hir::Look::WordStartUnicode",
          "norm": null,
          "value": "true",
          "line": 1551,
          "bound": null
        },
        {
          "cond": "*anchor matches hir::Look::WordStartUnicode",
          "norm": null,
          "value": "true",
          "line": 1551,
          "bound": null
        },
        {
          "cond": "self.add_look(look)?",
          "norm": null,
          "value": "Ok/Some",
          "line": 1571,
          "bound": null
        }
      ],
      "ret": "Ok(ThompsonRef { start: id, end: id })",
      "path": [
        0,
        14,
        32,
        37,
        38,
        39,
        42,
        45,
        48
      ],
      "may_contra": false,
      "min_set": true
    },
    {
      "id": 13,
      "conds": [
        {
          "cond": "*anchor matches hir::Look::WordEndAscii",
          "norm": null,
          "value": "true",
          "line": 1551,
          "bound": null
        },
        {
          "cond": "*anchor matches hir::Look::WordEndAscii",
          "norm": null,
          "value": "true",
          "line": 1551,
          "bound": null
        },
        {
          "cond": "self.add_look(look)?",
          "norm": null,
          "value": "Err/None",
          "line": 1571,
          "bound": null
        }
      ],
      "ret": null,
      "path": [
        0,
        13,
        31,
        37,
        38,
        39,
        41,
        43,
        44,
        46,
        47,
        48
      ],
      "may_contra": false,
      "min_set": false
    },
    {
      "id": 14,
      "conds": [
        {
          "cond": "*anchor matches hir::Look::WordEndAscii",
          "norm": null,
          "value": "true",
          "line": 1551,
          "bound": null
        },
        {
          "cond": "*anchor matches hir::Look::WordEndAscii",
          "norm": null,
          "value": "true",
          "line": 1551,
          "bound": null
        },
        {
          "cond": "self.add_look(look)?",
          "norm": null,
          "value": "Ok/Some",
          "line": 1571,
          "bound": null
        }
      ],
      "ret": "Ok(ThompsonRef { start: id, end: id })",
      "path": [
        0,
        13,
        31,
        37,
        38,
        39,
        42,
        45,
        48
      ],
      "may_contra": false,
      "min_set": true
    },
    {
      "id": 15,
      "conds": [
        {
          "cond": "*anchor matches hir::Look::WordStartAscii",
          "norm": null,
          "value": "true",
          "line": 1551,
          "bound": null
        },
        {
          "cond": "*anchor matches hir::Look::WordStartAscii",
          "norm": null,
          "value": "true",
          "line": 1551,
          "bound": null
        },
        {
          "cond": "self.add_look(look)?",
          "norm": null,
          "value": "Err/None",
          "line": 1571,
          "bound": null
        }
      ],
      "ret": null,
      "path": [
        0,
        12,
        30,
        37,
        38,
        39,
        41,
        43,
        44,
        46,
        47,
        48
      ],
      "may_contra": false,
      "min_set": false
    },
    {
      "id": 16,
      "conds": [
        {
          "cond": "*anchor matches hir::Look::WordStartAscii",
          "norm": null,
          "value": "true",
          "line": 1551,
          "bound": null
        },
        {
          "cond": "*anchor matches hir::Look::WordStartAscii",
          "norm": null,
          "value": "true",
          "line": 1551,
          "bound": null
        },
        {
          "cond": "self.add_look(look)?",
          "norm": null,
          "value": "Ok/Some",
          "line": 1571,
          "bound": null
        }
      ],
      "ret": "Ok(ThompsonRef { start: id, end: id })",
      "path": [
        0,
        12,
        30,
        37,
        38,
        39,
        42,
        45,
        48
      ],
      "may_contra": false,
      "min_set": true
    },
    {
      "id": 17,
      "conds": [
        {
          "cond": "*anchor matches hir::Look::WordUnicodeNegate",
          "norm": null,
          "value": "true",
          "line": 1551,
          "bound": null
        },
        {
          "cond": "*anchor matches hir::Look::WordUnicodeNegate",
          "norm": null,
          "value": "true",
          "line": 1551,
          "bound": null
        },
        {
          "cond": "self.add_look(look)?",
          "norm": null,
          "value": "Err/None",
          "line": 1571,
          "bound": null
        }
      ],
      "ret": null,
      "path": [
        0,
        11,
        29,
        37,
        38,
        39,
        41,
        43,
        44,
        46,
        47,
        48
      ],
      "may_contra": false,
      "min_set": false
    },
    {
      "id": 18,
      "conds": [
        {
          "cond": "*anchor matches hir::Look::WordUnicodeNegate",
          "norm": null,
          "value": "true",
          "line": 1551,
          "bound": null
        },
        {
          "cond": "*anchor matches hir::Look::WordUnicodeNegate",
          "norm": null,
          "value": "true",
          "line": 1551,
          "bound": null
        },
        {
          "cond": "self.add_look(look)?",
          "norm": null,
          "value": "Ok/Some",
          "line": 1571,
          "bound": null
        }
      ],
      "ret": "Ok(ThompsonRef { start: id, end: id })",
      "path": [
        0,
        11,
        29,
        37,
        38,
        39,
        42,
        45,
        48
      ],
      "may_contra": false,
      "min_set": true
    },
    {
      "id": 19,
      "conds": [
        {
          "cond": "*anchor matches hir::Look::WordUnicode",
          "norm": null,
          "value": "true",
          "line": 1551,
          "bound": null
        },
        {
          "cond": "*anchor matches hir::Look::WordUnicode",
          "norm": null,
          "value": "true",
          "line": 1551,
          "bound": null
        },
        {
          "cond": "self.add_look(look)?",
          "norm": null,
          "value": "Err/None",
          "line": 1571,
          "bound": null
        }
      ],
      "ret": null,
      "path": [
        0,
        10,
        28,
        37,
        38,
        39,
        41,
        43,
        44,
        46,
        47,
        48
      ],
      "may_contra": false,
      "min_set": false
    },
    {
      "id": 20,
      "conds": [
        {
          "cond": "*anchor matches hir::Look::WordUnicode",
          "norm": null,
          "value": "true",
          "line": 1551,
          "bound": null
        },
        {
          "cond": "*anchor matches hir::Look::WordUnicode",
          "norm": null,
          "value": "true",
          "line": 1551,
          "bound": null
        },
        {
          "cond": "self.add_look(look)?",
          "norm": null,
          "value": "Ok/Some",
          "line": 1571,
          "bound": null
        }
      ],
      "ret": "Ok(ThompsonRef { start: id, end: id })",
      "path": [
        0,
        10,
        28,
        37,
        38,
        39,
        42,
        45,
        48
      ],
      "may_contra": false,
      "min_set": true
    },
    {
      "id": 21,
      "conds": [
        {
          "cond": "*anchor matches hir::Look::WordAsciiNegate",
          "norm": null,
          "value": "true",
          "line": 1551,
          "bound": null
        },
        {
          "cond": "*anchor matches hir::Look::WordAsciiNegate",
          "norm": null,
          "value": "true",
          "line": 1551,
          "bound": null
        },
        {
          "cond": "self.add_look(look)?",
          "norm": null,
          "value": "Err/None",
          "line": 1571,
          "bound": null
        }
      ],
      "ret": null,
      "path": [
        0,
        9,
        27,
        37,
        38,
        39,
        41,
        43,
        44,
        46,
        47,
        48
      ],
      "may_contra": false,
      "min_set": false
    },
    {
      "id": 22,
      "conds": [
        {
          "cond": "*anchor matches hir::Look::WordAsciiNegate",
          "norm": null,
          "value": "true",
          "line": 1551,
          "bound": null
        },
        {
          "cond": "*anchor matches hir::Look::WordAsciiNegate",
          "norm": null,
          "value": "true",
          "line": 1551,
          "bound": null
        },
        {
          "cond": "self.add_look(look)?",
          "norm": null,
          "value": "Ok/Some",
          "line": 1571,
          "bound": null
        }
      ],
      "ret": "Ok(ThompsonRef { start: id, end: id })",
      "path": [
        0,
        9,
        27,
        37,
        38,
        39,
        42,
        45,
        48
      ],
      "may_contra": false,
      "min_set": true
    },
    {
      "id": 23,
      "conds": [
        {
          "cond": "*anchor matches hir::Look::WordAscii",
          "norm": null,
          "value": "true",
          "line": 1551,
          "bound": null
        },
        {
          "cond": "*anchor matches hir::Look::WordAscii",
          "norm": null,
          "value": "true",
          "line": 1551,
          "bound": null
        },
        {
          "cond": "self.add_look(look)?",
          "norm": null,
          "value": "Err/None",
          "line": 1571,
          "bound": null
        }
      ],
      "ret": null,
      "path": [
        0,
        8,
        26,
        37,
        38,
        39,
        41,
        43,
        44,
        46,
        47,
        48
      ],
      "may_contra": false,
      "min_set": false
    },
    {
      "id": 24,
      "conds": [
        {
          "cond": "*anchor matches hir::Look::WordAscii",
          "norm": null,
          "value": "true",
          "line": 1551,
          "bound": null
        },
        {
          "cond": "*anchor matches hir::Look::WordAscii",
          "norm": null,
          "value": "true",
          "line": 1551,
          "bound": null
        },
        {
          "cond": "self.add_look(look)?",
          "norm": null,
          "value": "Ok/Some",
          "line": 1571,
          "bound": null
        }
      ],
      "ret": "Ok(ThompsonRef { start: id, end: id })",
      "path": [
        0,
        8,
        26,
        37,
        38,
        39,
        42,
        45,
        48
      ],
      "may_contra": false,
      "min_set": true
    },
    {
      "id": 25,
      "conds": [
        {
          "cond": "*anchor matches hir::Look::EndCRLF",
          "norm": null,
          "value": "true",
          "line": 1551,
          "bound": null
        },
        {
          "cond": "*anchor matches hir::Look::EndCRLF",
          "norm": null,
          "value": "true",
          "line": 1551,
          "bound": null
        },
        {
          "cond": "self.add_look(look)?",
          "norm": null,
          "value": "Err/None",
          "line": 1571,
          "bound": null
        }
      ],
      "ret": null,
      "path": [
        0,
        7,
        25,
        37,
        38,
        39,
        41,
        43,
        44,
        46,
        47,
        48
      ],
      "may_contra": false,
      "min_set": false
    },
    {
      "id": 26,
      "conds": [
        {
          "cond": "*anchor matches hir::Look::EndCRLF",
          "norm": null,
          "value": "true",
          "line": 1551,
          "bound": null
        },
        {
          "cond": "*anchor matches hir::Look::EndCRLF",
          "norm": null,
          "value": "true",
          "line": 1551,
          "bound": null
        },
        {
          "cond": "self.add_look(look)?",
          "norm": null,
          "value": "Ok/Some",
          "line": 1571,
          "bound": null
        }
      ],
      "ret": "Ok(ThompsonRef { start: id, end: id })",
      "path": [
        0,
        7,
        25,
        37,
        38,
        39,
        42,
        45,
        48
      ],
      "may_contra": false,
      "min_set": true
    },
    {
      "id": 27,
      "conds": [
        {
          "cond": "*anchor matches hir::Look::StartCRLF",
          "norm": null,
          "value": "true",
          "line": 1551,
          "bound": null
        },
        {
          "cond": "*anchor matches hir::Look::StartCRLF",
          "norm": null,
          "value": "true",
          "line": 1551,
          "bound": null
        },
        {
          "cond": "self.add_look(look)?",
          "norm": null,
          "value": "Err/None",
          "line": 1571,
          "bound": null
        }
      ],
      "ret": null,
      "path": [
        0,
        6,
        24,
        37,
        38,
        39,
        41,
        43,
        44,
        46,
        47,
        48
      ],
      "may_contra": false,
      "min_set": false
    },
    {
      "id": 28,
      "conds": [
        {
          "cond": "*anchor matches hir::Look::StartCRLF",
          "norm": null,
          "value": "true",
          "line": 1551,
          "bound": null
        },
        {
          "cond": "*anchor matches hir::Look::StartCRLF",
          "norm": null,
          "value": "true",
          "line": 1551,
          "bound": null
        },
        {
          "cond": "self.add_look(look)?",
          "norm": null,
          "value": "Ok/Some",
          "line": 1571,
          "bound": null
        }
      ],
      "ret": "Ok(ThompsonRef { start: id, end: id })",
      "path": [
        0,
        6,
        24,
        37,
        38,
        39,
        42,
        45,
        48
      ],
      "may_contra": false,
      "min_set": true
    },
    {
      "id": 29,
      "conds": [
        {
          "cond": "*anchor matches hir::Look::EndLF",
          "norm": null,
          "value": "true",
          "line": 1551,
          "bound": null
        },
        {
          "cond": "*anchor matches hir::Look::EndLF",
          "norm": null,
          "value": "true",
          "line": 1551,
          "bound": null
        },
        {
          "cond": "self.add_look(look)?",
          "norm": null,
          "value": "Err/None",
          "line": 1571,
          "bound": null
        }
      ],
      "ret": null,
      "path": [
        0,
        5,
        23,
        37,
        38,
        39,
        41,
        43,
        44,
        46,
        47,
        48
      ],
      "may_contra": false,
      "min_set": false
    },
    {
      "id": 30,
      "conds": [
        {
          "cond": "*anchor matches hir::Look::EndLF",
          "norm": null,
          "value": "true",
          "line": 1551,
          "bound": null
        },
        {
          "cond": "*anchor matches hir::Look::EndLF",
          "norm": null,
          "value": "true",
          "line": 1551,
          "bound": null
        },
        {
          "cond": "self.add_look(look)?",
          "norm": null,
          "value": "Ok/Some",
          "line": 1571,
          "bound": null
        }
      ],
      "ret": "Ok(ThompsonRef { start: id, end: id })",
      "path": [
        0,
        5,
        23,
        37,
        38,
        39,
        42,
        45,
        48
      ],
      "may_contra": false,
      "min_set": true
    },
    {
      "id": 31,
      "conds": [
        {
          "cond": "*anchor matches hir::Look::StartLF",
          "norm": null,
          "value": "true",
          "line": 1551,
          "bound": null
        },
        {
          "cond": "*anchor matches hir::Look::StartLF",
          "norm": null,
          "value": "true",
          "line": 1551,
          "bound": null
        },
        {
          "cond": "self.add_look(look)?",
          "norm": null,
          "value": "Err/None",
          "line": 1571,
          "bound": null
        }
      ],
      "ret": null,
      "path": [
        0,
        4,
        22,
        37,
        38,
        39,
        41,
        43,
        44,
        46,
        47,
        48
      ],
      "may_contra": false,
      "min_set": false
    },
    {
      "id": 32,
      "conds": [
        {
          "cond": "*anchor matches hir::Look::StartLF",
          "norm": null,
          "value": "true",
          "line": 1551,
          "bound": null
        },
        {
          "cond": "*anchor matches hir::Look::StartLF",
          "norm": null,
          "value": "true",
          "line": 1551,
          "bound": null
        },
        {
          "cond": "self.add_look(look)?",
          "norm": null,
          "value": "Ok/Some",
          "line": 1571,
          "bound": null
        }
      ],
      "ret": "Ok(ThompsonRef { start: id, end: id })",
      "path": [
        0,
        4,
        22,
        37,
        38,
        39,
        42,
        45,
        48
      ],
      "may_contra": false,
      "min_set": true
    },
    {
      "id": 33,
      "conds": [
        {
          "cond": "*anchor matches hir::Look::End",
          "norm": null,
          "value": "true",
          "line": 1551,
          "bound": null
        },
        {
          "cond": "*anchor matches hir::Look::End",
          "norm": null,
          "value": "true",
          "line": 1551,
          "bound": null
        },
        {
          "cond": "self.add_look(look)?",
          "norm": null,
          "value": "Err/None",
          "line": 1571,
          "bound": null
        }
      ],
      "ret": null,
      "path": [
        0,
        3,
        21,
        37,
        38,
        39,
        41,
        43,
        44,
        46,
        47,
        48
      ],
      "may_contra": false,
      "min_set": true
    },
    {
      "id": 34,
      "conds": [
        {
          "cond": "*anchor matches hir::Look::End",
          "norm": null,
          "value": "true",
          "line": 1551,
          "bound": null
        },
        {
          "cond": "*anchor matches hir::Look::End",
          "norm": null,
          "value": "true",
          "line": 1551,
          "bound": null
        },
        {
          "cond": "self.add_look(look)?",
          "norm": null,
          "value": "Ok/Some",
          "line": 1571,
          "bound": null
        }
      ],
      "ret": "Ok(ThompsonRef { start: id, end: id })",
      "path": [
        0,
        3,
        21,
        37,
        38,
        39,
        42,
        45,
        48
      ],
      "may_contra": false,
      "min_set": false
    },
    {
      "id": 35,
      "conds": [
        {
          "cond": "*anchor matches hir::Look::Start",
          "norm": null,
          "value": "true",
          "line": 1551,
          "bound": null
        },
        {
          "cond": "*anchor matches hir::Look::Start",
          "norm": null,
          "value": "true",
          "line": 1551,
          "bound": null
        },
        {
          "cond": "self.add_look(look)?",
          "norm": null,
          "value": "Err/None",
          "line": 1571,
          "bound": null
        }
      ],
      "ret": null,
      "path": [
        0,
        2,
        20,
        37,
        38,
        39,
        41,
        43,
        44,
        46,
        47,
        48
      ],
      "may_contra": false,
      "min_set": false
    },
    {
      "id": 36,
      "conds": [
        {
          "cond": "*anchor matches hir::Look::Start",
          "norm": null,
          "value": "true",
          "line": 1551,
          "bound": null
        },
        {
          "cond": "*anchor matches hir::Look::Start",
          "norm": null,
          "value": "true",
          "line": 1551,
          "bound": null
        },
        {
          "cond": "self.add_look(look)?",
          "norm": null,
          "value": "Ok/Some",
          "line": 1571,
          "bound": null
        }
      ],
      "ret": "Ok(ThompsonRef { start: id, end: id })",
      "path": [
        0,
        2,
        20,
        37,
        38,
        39,
        42,
        45,
        48
      ],
      "may_contra": false,
      "min_set": true
    }
  ]
}