[
  {
    "uses": [],
    "has_test_mod": false,
    "common": [],
    "chain_tests": [
      {
        "attrs": [],
        "prefix": [
          "{",
          "    let compiler = Compiler {",
          "        parser: ParserBuilder::new(),",
          "        config: Config::default(),",
          "        builder: RefCell::new(Builder::default()),",
          "        utf8_state: RefCell::new(Utf8State {",
          "            compiled: Utf8BoundedMap::default(),",
          "            uncompiled: Vec::new(),",
          "        }),",
          "        trie_state: RefCell::new(RangeTrie::default()),",
          "        utf8_suffix: RefCell::new(Utf8SuffixMap {",
          "            version: 0,",
          "            capacity: 0,",
          "            map: Vec::new(),",
          "        }),",
          "    };",
          "    let anchor = hir::Look::Start;",
          "    let _ = compiler.c_look(&anchor);",
          "}"
        ],
        "oracle": [
          "    let compiler = Compiler { parser: ParserBuilder::new(), config: Config::default(), builder: RefCell::new(Builder::default()), utf8_state: RefCell::new(Utf8State { compiled: Utf8BoundedMap::default(), uncompiled: Vec::new(), }), trie_state: RefCell::new(RangeTrie::default()), utf8_suffix: RefCell::new(Utf8SuffixMap { version: 0, capacity: 0, map: Vec::new(), }), };",
          "    let anchor = hir::Look::StartCRLF;",
          "    let result = compiler.c_look(&anchor);",
          "    assert!(result.is_ok());",
          "    let thompson_ref = result.unwrap();",
          "    assert_eq!(thompson_ref.start, thompson_ref.end);"
        ],
        "code": [
          "{",
          "    let compiler = Compiler {",
          "        parser: ParserBuilder::new(),",
          "        config: Config::default(),",
          "        builder: RefCell::new(Builder::default()),",
          "        utf8_state: RefCell::new(Utf8State {",
          "            compiled: Utf8BoundedMap::default(),",
          "            uncompiled: Vec::new(),",
          "        }),",
          "        trie_state: RefCell::new(RangeTrie::default()),",
          "        utf8_suffix: RefCell::new(Utf8SuffixMap {",
          "            version: 0,",
          "            capacity: 0,",
          "            map: Vec::new(),",
          "        }),",
          "    };",
          "    let anchor = hir::Look::Start;",
          "    let _ = compiler.c_look(&anchor);",
          "    let compiler = Compiler { parser: ParserBuilder::new(), config: Config::default(), builder: RefCell::new(Builder::default()), utf8_state: RefCell::new(Utf8State { compiled: Utf8BoundedMap::default(), uncompiled: Vec::new(), }), trie_state: RefCell::new(RangeTrie::default()), utf8_suffix: RefCell::new(Utf8SuffixMap { version: 0, capacity: 0, map: Vec::new(), }), };",
          "    let anchor = hir::Look::StartCRLF;",
          "    let result = compiler.c_look(&anchor);",
          "    assert!(result.is_ok());",
          "    let thompson_ref = result.unwrap();",
          "    assert_eq!(thompson_ref.start, thompson_ref.end);",
          "}"
        ],
        "can_compile": false,
        "repaired": false
      },
      {
        "attrs": [],
        "prefix": [
          "{",
          "    let compiler = Compiler {",
          "        parser: ParserBuilder::new(),",
          "        config: Config::default(),",
          "        builder: RefCell::new(Builder::default()),",
          "        utf8_state: RefCell::new(Utf8State {",
          "            compiled: Utf8BoundedMap::default(),",
          "            uncompiled: Vec::new(),",
          "        }),",
          "        trie_state: RefCell::new(RangeTrie::default()),",
          "        utf8_suffix: RefCell::new(Utf8SuffixMap {",
          "            version: 0,",
          "            capacity: 0,",
          "            map: Vec::new(),",
          "        }),",
          "    };",
          "    let anchor = hir::Look::End;",
          "    let _ = compiler.c_look(&anchor);",
          "}"
        ],
        "oracle": [
          "    let anchor = hir::Look::StartCRLF;",
          "    let result = compiler.c_look(&anchor);",
          "    assert!(result.is_ok());",
          "    let thompson_ref = result.unwrap();",
          "    assert_eq!(thompson_ref.start, thompson_ref.end);",
          "    assert!(thompson_ref.start != StateID::ZERO);"
        ],
        "code": [
          "{",
          "    let compiler = Compiler {",
          "        parser: ParserBuilder::new(),",
          "        config: Config::default(),",
          "        builder: RefCell::new(Builder::default()),",
          "        utf8_state: RefCell::new(Utf8State {",
          "            compiled: Utf8BoundedMap::default(),",
          "            uncompiled: Vec::new(),",
          "        }),",
          "        trie_state: RefCell::new(RangeTrie::default()),",
          "        utf8_suffix: RefCell::new(Utf8SuffixMap {",
          "            version: 0,",
          "            capacity: 0,",
          "            map: Vec::new(),",
          "        }),",
          "    };",
          "    let anchor = hir::Look::End;",
          "    let _ = compiler.c_look(&anchor);",
          "    let anchor = hir::Look::StartCRLF;",
          "    let result = compiler.c_look(&anchor);",
          "    assert!(result.is_ok());",
          "    let thompson_ref = result.unwrap();",
          "    assert_eq!(thompson_ref.start, thompson_ref.end);",
          "    assert!(thompson_ref.start != StateID::ZERO);",
          "}"
        ],
        "can_compile": false,
        "repaired": false
      },
      {
        "attrs": [],
        "prefix": [
          "{",
          "    let compiler = Compiler {",
          "        parser: ParserBuilder::new(),",
          "        config: Config::default(),",
          "        builder: RefCell::new(Builder::default()),",
          "        utf8_state: RefCell::new(Utf8State {",
          "            compiled: Utf8BoundedMap::default(),",
          "            uncompiled: Vec::new(),",
          "        }),",
          "        trie_state: RefCell::new(RangeTrie::default()),",
          "        utf8_suffix: RefCell::new(Utf8SuffixMap {",
          "            version: 0,",
          "            capacity: 0,",
          "            map: Vec::new(),",
          "        }),",
          "    };",
          "    let anchor = hir::Look::StartLF;",
          "    let _ = compiler.c_look(&anchor);",
          "}"
        ],
        "oracle": [
          "    assert_eq!(compiler.c_look(&hir::Look::StartCRLF), Ok(ThompsonRef { start: id, end: id }));",
          "    assert!(matches!(compiler.add_look(Look::StartCRLF), Ok(_)));"
        ],
        "code": [
          "{",
          "    let compiler = Compiler {",
          "        parser: ParserBuilder::new(),",
          "        config: Config::default(),",
          "        builder: RefCell::new(Builder::default()),",
          "        utf8_state: RefCell::new(Utf8State {",
          "            compiled: Utf8BoundedMap::default(),",
          "            uncompiled: Vec::new(),",
          "        }),",
          "        trie_state: RefCell::new(RangeTrie::default()),",
          "        utf8_suffix: RefCell::new(Utf8SuffixMap {",
          "            version: 0,",
          "            capacity: 0,",
          "            map: Vec::new(),",
          "        }),",
          "    };",
          "    let anchor = hir::Look::StartLF;",
          "    let _ = compiler.c_look(&anchor);",
          "    assert_eq!(compiler.c_look(&hir::Look::StartCRLF), Ok(ThompsonRef { start: id, end: id }));",
          "    assert!(matches!(compiler.add_look(Look::StartCRLF), Ok(_)));",
          "}"
        ],
        "can_compile": false,
        "repaired": false
      },
      {
        "attrs": [],
        "prefix": [
          "{",
          "    let compiler = Compiler {",
          "        parser: ParserBuilder::new(),",
          "        config: Config::default(),",
          "        builder: RefCell::new(Builder::default()),",
          "        utf8_state: RefCell::new(Utf8State {",
          "            compiled: Utf8BoundedMap::default(),",
          "            uncompiled: Vec::new(),",
          "        }),",
          "        trie_state: RefCell::new(RangeTrie::default()),",
          "        utf8_suffix: RefCell::new(Utf8SuffixMap {",
          "            version: 0,",
          "            capacity: 0,",
          "            map: Vec::new(),",
          "        }),",
          "    };",
          "    let anchor = hir::Look::EndLF;",
          "    let _ = compiler.c_look(&anchor);",
          "}"
        ],
        "oracle": [
          "    let compiler = Compiler { parser: ParserBuilder::new(), config: Config::default(), builder: RefCell::new(Builder::default()), utf8_state: RefCell::new(Utf8State { compiled: Utf8BoundedMap::default(), uncompiled: Vec::new(), }), trie_state: RefCell::new(RangeTrie::default()), utf8_suffix: RefCell::new(Utf8SuffixMap { version: 0, capacity: 0, map: Vec::new(), }), };",
          "    let anchor = hir::Look::StartCRLF;",
          "    let result = compiler.c_look(&anchor);",
          "    assert!(result.is_ok());",
          "    let thompson_ref = result.unwrap();",
          "    assert_eq!(thompson_ref.start, thompson_ref.end);"
        ],
        "code": [
          "{",
          "    let compiler = Compiler {",
          "        parser: ParserBuilder::new(),",
          "        config: Config::default(),",
          "        builder: RefCell::new(Builder::default()),",
          "        utf8_state: RefCell::new(Utf8State {",
          "            compiled: Utf8BoundedMap::default(),",
          "            uncompiled: Vec::new(),",
          "        }),",
          "        trie_state: RefCell::new(RangeTrie::default()),",
          "        utf8_suffix: RefCell::new(Utf8SuffixMap {",
          "            version: 0,",
          "            capacity: 0,",
          "            map: Vec::new(),",
          "        }),",
          "    };",
          "    let anchor = hir::Look::EndLF;",
          "    let _ = compiler.c_look(&anchor);",
          "    let compiler = Compiler { parser: ParserBuilder::new(), config: Config::default(), builder: RefCell::new(Builder::default()), utf8_state: RefCell::new(Utf8State { compiled: Utf8BoundedMap::default(), uncompiled: Vec::new(), }), trie_state: RefCell::new(RangeTrie::default()), utf8_suffix: RefCell::new(Utf8SuffixMap { version: 0, capacity: 0, map: Vec::new(), }), };",
          "    let anchor = hir::Look::StartCRLF;",
          "    let result = compiler.c_look(&anchor);",
          "    assert!(result.is_ok());",
          "    let thompson_ref = result.unwrap();",
          "    assert_eq!(thompson_ref.start, thompson_ref.end);",
          "}"
        ],
        "can_compile": false,
        "repaired": false
      },
      {
        "attrs": [],
        "prefix": [
          "{",
          "    let compiler = Compiler {",
          "        parser: ParserBuilder::new(),",
          "        config: Config::default(),",
          "        builder: RefCell::new(Builder::default()),",
          "        utf8_state: RefCell::new(Utf8State {",
          "            compiled: Utf8BoundedMap::default(),",
          "            uncompiled: Vec::new(),",
          "        }),",
          "        trie_state: RefCell::new(RangeTrie::default()),",
          "        utf8_suffix: RefCell::new(Utf8SuffixMap {",
          "            version: 0,",
          "            capacity: 0,",
          "            map: Vec::new(),",
          "        }),",
          "    };",
          "    let anchor = hir::Look::WordAscii;",
          "    let _ = compiler.c_look(&anchor);",
          "}"
        ],
        "oracle": [
          "    let anchor = hir::Look::StartCRLF;",
          "    assert_eq!(compiler.c_look(&anchor).is_ok(), true);",
          "    let result = compiler.c_look(&anchor).unwrap();",
          "    assert_eq!(result.start, result.end);",
          "    assert_eq!(result.start, compiler.add_look(Look::StartCRLF).unwrap());"
        ],
        "code": [
          "{",
          "    let compiler = Compiler {",
          "        parser: ParserBuilder::new(),",
          "        config: Config::default(),",
          "        builder: RefCell::new(Builder::default()),",
          "        utf8_state: RefCell::new(Utf8State {",
          "            compiled: Utf8BoundedMap::default(),",
          "            uncompiled: Vec::new(),",
          "        }),",
          "        trie_state: RefCell::new(RangeTrie::default()),",
          "        utf8_suffix: RefCell::new(Utf8SuffixMap {",
          "            version: 0,",
          "            capacity: 0,",
          "            map: Vec::new(),",
          "        }),",
          "    };",
          "    let anchor = hir::Look::WordAscii;",
          "    let _ = compiler.c_look(&anchor);",
          "    let anchor = hir::Look::StartCRLF;",
          "    assert_eq!(compiler.c_look(&anchor).is_ok(), true);",
          "    let result = compiler.c_look(&anchor).unwrap();",
          "    assert_eq!(result.start, result.end);",
          "    assert_eq!(result.start, compiler.add_look(Look::StartCRLF).unwrap());",
          "}"
        ],
        "can_compile": false,
        "repaired": false
      },
      {
        "attrs": [],
        "prefix": [
          "{",
          "    let compiler = Compiler {",
          "        parser: ParserBuilder::new(),",
          "        config: Config::default(),",
          "        builder: RefCell::new(Builder::default()),",
          "        utf8_state: RefCell::new(Utf8State {",
          "            compiled: Utf8BoundedMap::default(),",
          "            uncompiled: Vec::new(),",
          "        }),",
          "        trie_state: RefCell::new(RangeTrie::default()),",
          "        utf8_suffix: RefCell::new(Utf8SuffixMap {",
          "            version: 0,",
          "            capacity: 0,",
          "            map: Vec::new(),",
          "        }),",
          "    };",
          "    let anchor = hir::Look::WordUnicode;",
          "    let _ = compiler.c_look(&anchor);",
          "}"
        ],
        "oracle": [
          "    let compiler = Compiler {",
          "    parser: ParserBuilder::new(),",
          "    config: Config::default(),",
          "    builder: RefCell::new(Builder::default()),",
          "    utf8_state: RefCell::new(Utf8State {",
          "    compiled: Utf8BoundedMap::default(),",
          "    uncompiled: Vec::new(),",
          "    }),",
          "    trie_state: RefCell::new(RangeTrie::default()),",
          "    utf8_suffix: RefCell::new(Utf8SuffixMap {",
          "    version: 0,",
          "    capacity: 0,",
          "    map: Vec::new(),",
          "    }),",
          "    };",
          "    let anchor = hir::Look::StartCRLF;",
          "    let result = compiler.c_look(&anchor);",
          "    assert!(result.is_ok());",
          "    let thompson_ref = result.unwrap();",
          "    assert_eq!(thompson_ref.start, thompson_ref.end);"
        ],
        "code": [
          "{",
          "    let compiler = Compiler {",
          "        parser: ParserBuilder::new(),",
          "        config: Config::default(),",
          "        builder: RefCell::new(Builder::default()),",
          "        utf8_state: RefCell::new(Utf8State {",
          "            compiled: Utf8BoundedMap::default(),",
          "            uncompiled: Vec::new(),",
          "        }),",
          "        trie_state: RefCell::new(RangeTrie::default()),",
          "        utf8_suffix: RefCell::new(Utf8SuffixMap {",
          "            version: 0,",
          "            capacity: 0,",
          "            map: Vec::new(),",
          "        }),",
          "    };",
          "    let anchor = hir::Look::WordUnicode;",
          "    let _ = compiler.c_look(&anchor);",
          "    let compiler = Compiler {",
          "    parser: ParserBuilder::new(),",
          "    config: Config::default(),",
          "    builder: RefCell::new(Builder::default()),",
          "    utf8_state: RefCell::new(Utf8State {",
          "    compiled: Utf8BoundedMap::default(),",
          "    uncompiled: Vec::new(),",
          "    }),",
          "    trie_state: RefCell::new(RangeTrie::default()),",
          "    utf8_suffix: RefCell::new(Utf8SuffixMap {",
          "    version: 0,",
          "    capacity: 0,",
          "    map: Vec::new(),",
          "    }),",
          "    };",
          "    let anchor = hir::Look::StartCRLF;",
          "    let result = compiler.c_look(&anchor);",
          "    assert!(result.is_ok());",
          "    let thompson_ref = result.unwrap();",
          "    assert_eq!(thompson_ref.start, thompson_ref.end);",
          "}"
        ],
        "can_compile": false,
        "repaired": false
      },
      {
        "attrs": [],
        "prefix": [
          "{",
          "    let compiler = Compiler {",
          "        parser: ParserBuilder::new(),",
          "        config: Config::default(),",
          "        builder: RefCell::new(Builder::default()),",
          "        utf8_state: RefCell::new(Utf8State {",
          "            compiled: Utf8BoundedMap::default(),",
          "            uncompiled: Vec::new(),",
          "        }),",
          "        trie_state: RefCell::new(RangeTrie::default()),",
          "        utf8_suffix: RefCell::new(Utf8SuffixMap {",
          "            version: 0,",
          "            capacity: 0,",
          "            map: Vec::new(),",
          "        }),",
          "    };",
          "    let anchor = hir::Look::WordStartAscii;",
          "    let _ = compiler.c_look(&anchor);",
          "}"
        ],
        "oracle": [
          "    let compiler = Compiler { parser: ParserBuilder::new(), config: Config::default(), builder: RefCell::new(Builder::default()), utf8_state: RefCell::new(Utf8State { compiled: Utf8BoundedMap::default(), uncompiled: Vec::new(), }), trie_state: RefCell::new(RangeTrie::default()), utf8_suffix: RefCell::new(Utf8SuffixMap { version: 0, capacity: 0, map: Vec::new(), }), };",
          "    let anchor = hir::Look::StartCRLF;",
          "    let result = compiler.c_look(&anchor);",
          "    assert!(result.is_ok());",
          "    let thompson_ref = result.unwrap();",
          "    assert_eq!(thompson_ref.start, thompson_ref.end);"
        ],
        "code": [
          "{",
          "    let compiler = Compiler {",
          "        parser: ParserBuilder::new(),",
          "        config: Config::default(),",
          "        builder: RefCell::new(Builder::default()),",
          "        utf8_state: RefCell::new(Utf8State {",
          "            compiled: Utf8BoundedMap::default(),",
          "            uncompiled: Vec::new(),",
          "        }),",
          "        trie_state: RefCell::new(RangeTrie::default()),",
          "        utf8_suffix: RefCell::new(Utf8SuffixMap {",
          "            version: 0,",
          "            capacity: 0,",
          "            map: Vec::new(),",
          "        }),",
          "    };",
          "    let anchor = hir::Look::WordStartAscii;",
          "    let _ = compiler.c_look(&anchor);",
          "    let compiler = Compiler { parser: ParserBuilder::new(), config: Config::default(), builder: RefCell::new(Builder::default()), utf8_state: RefCell::new(Utf8State { compiled: Utf8BoundedMap::default(), uncompiled: Vec::new(), }), trie_state: RefCell::new(RangeTrie::default()), utf8_suffix: RefCell::new(Utf8SuffixMap { version: 0, capacity: 0, map: Vec::new(), }), };",
          "    let anchor = hir::Look::StartCRLF;",
          "    let result = compiler.c_look(&anchor);",
          "    assert!(result.is_ok());",
          "    let thompson_ref = result.unwrap();",
          "    assert_eq!(thompson_ref.start, thompson_ref.end);",
          "}"
        ],
        "can_compile": false,
        "repaired": false
      },
      {
        "attrs": [],
        "prefix": [
          "{",
          "    let compiler = Compiler {",
          "        parser: ParserBuilder::new(),",
          "        config: Config::default(),",
          "        builder: RefCell::new(Builder::default()),",
          "        utf8_state: RefCell::new(Utf8State {",
          "            compiled: Utf8BoundedMap::default(),",
          "            uncompiled: Vec::new(),",
          "        }),",
          "        trie_state: RefCell::new(RangeTrie::default()),",
          "        utf8_suffix: RefCell::new(Utf8SuffixMap {",
          "            version: 0,",
          "            capacity: 0,",
          "            map: Vec::new(),",
          "        }),",
          "    };",
          "    let anchor = hir::Look::WordEndAscii;",
          "    let _ = compiler.c_look(&anchor);",
          "}"
        ],
        "oracle": [
          "    let compiler = Compiler { parser: ParserBuilder::new(), config: Config::default(), builder: RefCell::new(Builder::default()), utf8_state: RefCell::new(Utf8State { compiled: Utf8BoundedMap::default(), uncompiled: Vec::new(), }), trie_state: RefCell::new(RangeTrie::default()), utf8_suffix: RefCell::new(Utf8SuffixMap { version: 0, capacity: 0, map: Vec::new(), }), };",
          "    let anchor = hir::Look::StartCRLF;",
          "    let result = compiler.c_look(&anchor);",
          "    assert!(result.is_ok());",
          "    let thompson_ref = result.unwrap();",
          "    assert_eq!(thompson_ref.start, thompson_ref.end);"
        ],
        "code": [
          "{",
          "    let compiler = Compiler {",
          "        parser: ParserBuilder::new(),",
          "        config: Config::default(),",
          "        builder: RefCell::new(Builder::default()),",
          "        utf8_state: RefCell::new(Utf8State {",
          "            compiled: Utf8BoundedMap::default(),",
          "            uncompiled: Vec::new(),",
          "        }),",
          "        trie_state: RefCell::new(RangeTrie::default()),",
          "        utf8_suffix: RefCell::new(Utf8SuffixMap {",
          "            version: 0,",
          "            capacity: 0,",
          "            map: Vec::new(),",
          "        }),",
          "    };",
          "    let anchor = hir::Look::WordEndAscii;",
          "    let _ = compiler.c_look(&anchor);",
          "    let compiler = Compiler { parser: ParserBuilder::new(), config: Config::default(), builder: RefCell::new(Builder::default()), utf8_state: RefCell::new(Utf8State { compiled: Utf8BoundedMap::default(), uncompiled: Vec::new(), }), trie_state: RefCell::new(RangeTrie::default()), utf8_suffix: RefCell::new(Utf8SuffixMap { version: 0, capacity: 0, map: Vec::new(), }), };",
          "    let anchor = hir::Look::StartCRLF;",
          "    let result = compiler.c_look(&anchor);",
          "    assert!(result.is_ok());",
          "    let thompson_ref = result.unwrap();",
          "    assert_eq!(thompson_ref.start, thompson_ref.end);",
          "}"
        ],
        "can_compile": false,
        "repaired": false
      }
    ]
  }
]