{
  "name": "url::{impl#5}::from",
  "mod_info": {
    "name": "",
    "loc": "url/src/lib.rs:9:1:3218:2"
  },
  "visible": true,
  "loc": "url/src/lib.rs:2791:5:2793:6",
  "doc": "",
  "code": [
    "fn from(value: Url) -> String {",
    "    value.serialization",
    "}"
  ],
  "size": {
    "chain": 1,
    "contra": 0,
    "min_set": 1
  },
  "cond_chains": [
    {
      "id": 1,
      "conds": [],
      "ret": "value.serialization",
      "path": [
        0,
        1
      ],
      "may_contra": false,
      "min_set": true
    }
  ]
}