[
  {
    "uses": [],
    "has_test_mod": false,
    "common": [],
    "chain_tests": [
      {
        "attrs": [],
        "prefix": [
          "{",
          "    let look = Look::EndCRLF;",
          "    let result = look.reversed();",
          "}"
        ],
        "oracle": [
          "    assert_eq!(result, Look::StartCRLF);"
        ],
        "code": [
          "{",
          "    let look = Look::EndCRLF;",
          "    let result = look.reversed();",
          "    assert_eq!(result, Look::StartCRLF);",
          "}"
        ],
        "can_compile": false,
        "repaired": false
      },
      {
        "attrs": [],
        "prefix": [
          "{",
          "    let look = Look::StartCRLF;",
          "    let result = look.reversed();",
          "}"
        ],
        "oracle": [
          "    assert_eq!(result, Look::EndCRLF);"
        ],
        "code": [
          "{",
          "    let look = Look::StartCRLF;",
          "    let result = look.reversed();",
          "    assert_eq!(result, Look::EndCRLF);",
          "}"
        ],
        "can_compile": false,
        "repaired": false
      },
      {
        "attrs": [],
        "prefix": [
          "{",
          "    let look = Look::End;",
          "    let result = look.reversed();",
          "}"
        ],
        "oracle": [
          "    let look = Look::Start; assert_eq!(look.reversed(), Look::End);",
          "    let look = Look::End; assert_eq!(look.reversed(), Look::Start);",
          "    let look = Look::StartLF; assert_eq!(look.reversed(), Look::EndLF);",
          "    let look = Look::EndLF; assert_eq!(look.reversed(), Look::StartLF);",
          "    let look = Look::StartCRLF; assert_eq!(look.reversed(), Look::EndCRLF);",
          "    let look = Look::EndCRLF; assert_eq!(look.reversed(), Look::StartCRLF);",
          "    let look = Look::WordAscii; assert_eq!(look.reversed(), Look::WordAscii);",
          "    let look = Look::WordAsciiNegate; assert_eq!(look.reversed(), Look::WordAsciiNegate);",
          "    let look = Look::WordUnicode; assert_eq!(look.reversed(), Look::WordUnicode);",
          "    let look = Look::WordUnicodeNegate; assert_eq!(look.reversed(), Look::WordUnicodeNegate);",
          "    let look = Look::WordStartAscii; assert_eq!(look.reversed(), Look::WordEndAscii);",
          "    let look = Look::WordEndAscii; assert_eq!(look.reversed(), Look::WordStartAscii);",
          "    let look = Look::WordStartUnicode; assert_eq!(look.reversed(), Look::WordEndUnicode);",
          "    let look = Look::WordEndUnicode; assert_eq!(look.reversed(), Look::WordStartUnicode);",
          "    let look = Look::WordStartHalfAscii; assert_eq!(look.reversed(), Look::WordEndHalfAscii);",
          "    let look = Look::WordEndHalfAscii; assert_eq!(look.reversed(), Look::WordStartHalfAscii);",
          "    let look = Look::WordStartHalfUnicode; assert_eq!(look.reversed(), Look::WordEndHalfUnicode);",
          "    let look = Look::WordEndHalfUnicode; assert_eq!(look.reversed(), Look::WordStartHalfUnicode);"
        ],
        "code": [
          "{",
          "    let look = Look::End;",
          "    let result = look.reversed();",
          "    let look = Look::Start; assert_eq!(look.reversed(), Look::End);",
          "    let look = Look::End; assert_eq!(look.reversed(), Look::Start);",
          "    let look = Look::StartLF; assert_eq!(look.reversed(), Look::EndLF);",
          "    let look = Look::EndLF; assert_eq!(look.reversed(), Look::StartLF);",
          "    let look = Look::StartCRLF; assert_eq!(look.reversed(), Look::EndCRLF);",
          "    let look = Look::EndCRLF; assert_eq!(look.reversed(), Look::StartCRLF);",
          "    let look = Look::WordAscii; assert_eq!(look.reversed(), Look::WordAscii);",
          "    let look = Look::WordAsciiNegate; assert_eq!(look.reversed(), Look::WordAsciiNegate);",
          "    let look = Look::WordUnicode; assert_eq!(look.reversed(), Look::WordUnicode);",
          "    let look = Look::WordUnicodeNegate; assert_eq!(look.reversed(), Look::WordUnicodeNegate);",
          "    let look = Look::WordStartAscii; assert_eq!(look.reversed(), Look::WordEndAscii);",
          "    let look = Look::WordEndAscii; assert_eq!(look.reversed(), Look::WordStartAscii);",
          "    let look = Look::WordStartUnicode; assert_eq!(look.reversed(), Look::WordEndUnicode);",
          "    let look = Look::WordEndUnicode; assert_eq!(look.reversed(), Look::WordStartUnicode);",
          "    let look = Look::WordStartHalfAscii; assert_eq!(look.reversed(), Look::WordEndHalfAscii);",
          "    let look = Look::WordEndHalfAscii; assert_eq!(look.reversed(), Look::WordStartHalfAscii);",
          "    let look = Look::WordStartHalfUnicode; assert_eq!(look.reversed(), Look::WordEndHalfUnicode);",
          "    let look = Look::WordEndHalfUnicode; assert_eq!(look.reversed(), Look::WordStartHalfUnicode);",
          "}"
        ],
        "can_compile": false,
        "repaired": false
      },
      {
        "attrs": [],
        "prefix": [
          "{",
          "    let look = Look::Start;",
          "    let result = look.reversed();",
          "}"
        ],
        "oracle": [
          "    Look::Start.reversed() == Look::End",
          "    Look::End.reversed() == Look::Start",
          "    Look::StartLF.reversed() == Look::EndLF",
          "    Look::EndLF.reversed() == Look::StartLF",
          "    Look::StartCRLF.reversed() == Look::EndCRLF",
          "    Look::EndCRLF.reversed() == Look::StartCRLF",
          "    Look::WordAscii.reversed() == Look::WordAscii",
          "    Look::WordAsciiNegate.reversed() == Look::WordAsciiNegate",
          "    Look::WordUnicode.reversed() == Look::WordUnicode",
          "    Look::WordUnicodeNegate.reversed() == Look::WordUnicodeNegate",
          "    Look::WordStartAscii.reversed() == Look::WordEndAscii",
          "    Look::WordEndAscii.reversed() == Look::WordStartAscii",
          "    Look::WordStartUnicode.reversed() == Look::WordEndUnicode",
          "    Look::WordEndUnicode.reversed() == Look::WordStartUnicode",
          "    Look::WordStartHalfAscii.reversed() == Look::WordEndHalfAscii",
          "    Look::WordEndHalfAscii.reversed() == Look::WordStartHalfAscii",
          "    Look::WordStartHalfUnicode.reversed() == Look::WordEndHalfUnicode",
          "    Look::WordEndHalfUnicode.reversed() == Look::WordStartHalfUnicode"
        ],
        "code": [
          "{",
          "    let look = Look::Start;",
          "    let result = look.reversed();",
          "    Look::Start.reversed() == Look::End",
          "    Look::End.reversed() == Look::Start",
          "    Look::StartLF.reversed() == Look::EndLF",
          "    Look::EndLF.reversed() == Look::StartLF",
          "    Look::StartCRLF.reversed() == Look::EndCRLF",
          "    Look::EndCRLF.reversed() == Look::StartCRLF",
          "    Look::WordAscii.reversed() == Look::WordAscii",
          "    Look::WordAsciiNegate.reversed() == Look::WordAsciiNegate",
          "    Look::WordUnicode.reversed() == Look::WordUnicode",
          "    Look::WordUnicodeNegate.reversed() == Look::WordUnicodeNegate",
          "    Look::WordStartAscii.reversed() == Look::WordEndAscii",
          "    Look::WordEndAscii.reversed() == Look::WordStartAscii",
          "    Look::WordStartUnicode.reversed() == Look::WordEndUnicode",
          "    Look::WordEndUnicode.reversed() == Look::WordStartUnicode",
          "    Look::WordStartHalfAscii.reversed() == Look::WordEndHalfAscii",
          "    Look::WordEndHalfAscii.reversed() == Look::WordStartHalfAscii",
          "    Look::WordStartHalfUnicode.reversed() == Look::WordEndHalfUnicode",
          "    Look::WordEndHalfUnicode.reversed() == Look::WordStartHalfUnicode",
          "}"
        ],
        "can_compile": false,
        "repaired": false
      }
    ]
  }
]